mngs/__init__.py
mngs/__main__.py
mngs/_sh.py
mngs/ai/ClassificationReporter.py
mngs/ai/ClassifierServer.py
mngs/ai/EarlyStopping.py
mngs/ai/_LearningCurveLogger.py
mngs/ai/__Classifiers.py
mngs/ai/__init__.py
mngs/ai/_gen_ai/_Anthropic.py
mngs/ai/_gen_ai/_BaseGenAI.py
mngs/ai/_gen_ai/_DeepSeek.py
mngs/ai/_gen_ai/_Google.py
mngs/ai/_gen_ai/_Groq.py
mngs/ai/_gen_ai/_Llama.py
mngs/ai/_gen_ai/_OpenAI.py
mngs/ai/_gen_ai/_PARAMS.py
mngs/ai/_gen_ai/_Perplexity.py
mngs/ai/_gen_ai/__init__.py
mngs/ai/_gen_ai/_calc_cost.py
mngs/ai/_gen_ai/_format_output_func.py
mngs/ai/_gen_ai/_genai_factory.py
mngs/ai/act/__init__.py
mngs/ai/act/_define.py
mngs/ai/clustering/_UMAP.py
mngs/ai/clustering/__init__.py
mngs/ai/clustering/_pca.py
mngs/ai/clustering/_umap.py
mngs/ai/clustering/_umap_dev.py
mngs/ai/clustering/_umap_working.py
mngs/ai/feature_extraction/__init__.py
mngs/ai/feature_extraction/vit.py
mngs/ai/layer/_Pass.py
mngs/ai/layer/__init__.py
mngs/ai/layer/_switch.py
mngs/ai/loss/MultiTaskLoss.py
mngs/ai/loss/_L1L2Losses.py
mngs/ai/loss/__init__.py
mngs/ai/metrics/__init__.py
mngs/ai/metrics/_bACC.py
mngs/ai/metrics/silhoute_score_block.py
mngs/ai/optim/__init__.py
mngs/ai/optim/_get_set.py
mngs/ai/optim/Ranger_Deep_Learning_Optimizer/__init__.py
mngs/ai/optim/Ranger_Deep_Learning_Optimizer/setup.py
mngs/ai/optim/Ranger_Deep_Learning_Optimizer/ranger/__init__.py
mngs/ai/optim/Ranger_Deep_Learning_Optimizer/ranger/ranger.py
mngs/ai/optim/Ranger_Deep_Learning_Optimizer/ranger/ranger2020.py
mngs/ai/optim/Ranger_Deep_Learning_Optimizer/ranger/ranger913A.py
mngs/ai/optim/Ranger_Deep_Learning_Optimizer/ranger/rangerqh.py
mngs/ai/plt/__init__.py
mngs/ai/plt/_conf_mat.py
mngs/ai/plt/_learning_curve.py
mngs/ai/plt/_optuna_study.py
mngs/ai/plt/aucs/__init__.py
mngs/ai/plt/aucs/example.py
mngs/ai/plt/aucs/pre_rec_auc.py
mngs/ai/plt/aucs/roc_auc.py
mngs/ai/sk/__init__.py
mngs/ai/sk/_clf.py
mngs/ai/sk/_to_sktime.py
mngs/ai/utils/_DefaultDataset.py
mngs/ai/utils/_LabelEncoder.py
mngs-1.11.0.dist-info/LICENSE
mngs-1.11.0.dist-info/METADATA
mngs-1.11.0.dist-info/WHEEL
mngs-1.11.0.dist-info/top_level.txt
mngs-1.11.0.dist-info/RECORD
