Metadata-Version: 2.1
Name: mngs
Version: 1.11.0
Summary: For lazy python users (monogusa people in Japanse), especially in ML/DSP fields
Home-page: https://github.com/ywatanabe1989/mngs
Author: ywatanabe1989
Author-email: ywatanabe@alumni.u-tokyo.ac.jp
License: MIT
Keywords: utils,utilities,python,machine learning
Platform: UNKNOWN
Classifier: Programming Language :: Python :: 3
Classifier: License :: OSI Approved :: MIT License
Requires-Python: >=3.0
License-File: LICENSE
Requires-Dist: GitPython
Requires-Dist: Pillow
Requires-Dist: PyYAML
Requires-Dist: Pyarrow
Requires-Dist: accelerate
Requires-Dist: aiohttp
Requires-Dist: ansi-escapes
Requires-Dist: anthropic
Requires-Dist: attrdict
Requires-Dist: bitsandbytes
Requires-Dist: black
Requires-Dist: bs4
Requires-Dist: chardet
Requires-Dist: docutils
Requires-Dist: docutils<0.18
Requires-Dist: einops
Requires-Dist: epc
Requires-Dist: fairscale
Requires-Dist: fastapi
Requires-Dist: flake8
Requires-Dist: flask
Requires-Dist: geom-median
Requires-Dist: google-genai
Requires-Dist: google-search-results
Requires-Dist: googlesearch-python
Requires-Dist: groq
Requires-Dist: h5py
Requires-Dist: html2text
Requires-Dist: icecream
Requires-Dist: ipdb
Requires-Dist: ipython
Requires-Dist: isort
Requires-Dist: jedi
Requires-Dist: joblib
Requires-Dist: joypy
Requires-Dist: julius
Requires-Dist: llama-stack
Requires-Dist: lxml
Requires-Dist: lxml-html-clean
Requires-Dist: markdown
Requires-Dist: markdown2
Requires-Dist: matplotlib
Requires-Dist: matplotlib-venn
Requires-Dist: mne
Requires-Dist: more-itertools
Requires-Dist: natsort
Requires-Dist: numpy
Requires-Dist: obspy
Requires-Dist: openai
Requires-Dist: openpyxl
Requires-Dist: optuna
Requires-Dist: packaging
Requires-Dist: pandas
Requires-Dist: pebble
Requires-Dist: platformdirs
Requires-Dist: plotly
Requires-Dist: plyer
Requires-Dist: psutil
Requires-Dist: psycopg2-binary
Requires-Dist: pybids
Requires-Dist: pyedflib
Requires-Dist: pygments
Requires-Dist: pyls
Requires-Dist: pymatreader
Requires-Dist: pyperclip
Requires-Dist: pyright
Requires-Dist: pytest
Requires-Dist: pytest-cov
Requires-Dist: pytest-env
Requires-Dist: pytest-xdist
Requires-Dist: python-docx
Requires-Dist: python-lsp-server
Requires-Dist: pytorch-pretrained-vit
Requires-Dist: readability
Requires-Dist: readability-lxml
Requires-Dist: readchar
Requires-Dist: reportlab
Requires-Dist: requests
Requires-Dist: ripple-detection
Requires-Dist: ruamel.yaml
Requires-Dist: ruff-lsp
Requires-Dist: scikit-image
Requires-Dist: scikit-learn
Requires-Dist: scipy
Requires-Dist: seaborn
Requires-Dist: selenium
Requires-Dist: setuptools
Requires-Dist: six
Requires-Dist: sktime
Requires-Dist: sounddevice
Requires-Dist: sphinx
Requires-Dist: sqlalchemy
Requires-Dist: statsmodels
Requires-Dist: sympy
Requires-Dist: tabulate
Requires-Dist: tensorpac
Requires-Dist: termplotlib
Requires-Dist: timeout-decorator
Requires-Dist: tk
Requires-Dist: tldr
Requires-Dist: torch
Requires-Dist: torchaudio
Requires-Dist: torchsummary
Requires-Dist: torchvision
Requires-Dist: transformers
Requires-Dist: twine
Requires-Dist: umap-learn
Requires-Dist: webdriver-manager
Requires-Dist: wheel
Requires-Dist: xarray
Requires-Dist: xlrd
Requires-Dist: xmltodict
